{
  "data": [
    {
      "id": 11,
      "absolutePerformance": 3.4212,
      "alpha": 3.0912,
      "benchMarkTicker": "SPX",
      "benchMarkTickerDesk": "S\u0026P 500 Index",
      "benchMarkCurrentPrice": 2856.66,
      "benchMarkPerformance": 0.392,
      "convictionId": 1,
      "currentPrice": 24.59,
      "direction": "Long",
      "directionId": 1,
      "entryPrice": 348.213,
      "reason": "Target Price",
      "securityName": "Boeing",
      "stockCurrency": "USD",
      "stopLoss": 10,
      "stopLossValue": 313.4823,
      "targetPrice": 360.0,
      "targetPricePercentage": 0.0,
      "timeHorizon": "1 Week",
      "createdBy": "Dmitri"
    },
    {
      "id": 12,
      "absolutePerformance": 3.4212,
      "alpha": 3.0912,
      "benchMarkTicker": "SPX",
      "benchMarkTickerDesk": "S\u0026P 500 Index",
      "benchMarkCurrentPrice": 2856.66,
      "benchMarkPerformance": 0.392,
      "convictionId": 1,
      "currentPrice": 24.59,
      "direction": "Long",
      "directionId": 1,
      "entryPrice": 348.213,
      "reason": "Target Price",
      "securityName": "Target Corp",
      "stockCurrency": "USD",
      "stopLoss": 10,
      "stopLossValue": 313.4823,
      "targetPrice": 360.0,
      "targetPricePercentage": 0.0,
      "timeHorizon": "1 Week",
      "createdBy": "Dmitri"
    },
    {
      "id": 13,
      "absolutePerformance": 3.4212,
      "alpha": 3.0912,
      "benchMarkTicker": "SPX",
      "benchMarkTickerDesk": "S\u0026P 500 Index",
      "benchMarkCurrentPrice": 2856.66,
      "benchMarkPerformance": 0.392,
      "convictionId": 1,
      "currentPrice": 24.59,
      "direction": "Long",
      "directionId": 1,
      "entryPrice": 348.213,
      "reason": "Target Price",
      "securityName": "Amazon",
      "stockCurrency": "USD",
      "stopLoss": 10,
      "stopLossValue": 313.4823,
      "targetPrice": 360.0,
      "targetPricePercentage": 0.0,
      "timeHorizon": "1 Week",
      "createdBy": "Dmitri"
    }
  ]
}